drf_spreadsheets/__init__.py
drf_spreadsheets/mixins.py
drf_spreadsheets/renderers.py
drf_spreadsheets_jpaavola-1.0.0.dist-info/LICENSE.md
drf_spreadsheets_jpaavola-1.0.0.dist-info/METADATA
drf_spreadsheets_jpaavola-1.0.0.dist-info/WHEEL
drf_spreadsheets_jpaavola-1.0.0.dist-info/top_level.txt
drf_spreadsheets_jpaavola-1.0.0.dist-info/RECORD
