Metadata-Version: 2.1
Name: drf-spreadsheets-jpaavola
Version: 1.0.0
Summary: A Django REST Framework package allowing views to be rendered as CSV or XLSX
Home-page: https://github.com/jpaav/drf-spreadsheets
Author: Joe Paavola
Author-email: joepaavola@gmail.com
License: UNKNOWN
Platform: UNKNOWN
Classifier: Programming Language :: Python :: 3
Classifier: License :: OSI Approved :: MIT License
Classifier: Operating System :: OS Independent
Classifier: Framework :: Django
Requires-Python: >=3.6
Requires-Dist: Django (>=3.1)
Requires-Dist: djangorestframework (>=3.6)
Requires-Dist: openpyxl (>=2.4)
